terminusgps_install/__init__.py
terminusgps_install/admin.py
terminusgps_install/apps.py
terminusgps_install/forms.py
terminusgps_install/models.py
terminusgps_install/tests.py
terminusgps_install/urls.py
terminusgps_install/views.py
terminusgps_install/migrations/0001_initial.py
terminusgps_install/migrations/__init__.py
terminusgps_install/static/terminusgps_install/favicon.ico
terminusgps_install/static/terminusgps_install/js/htmx.min.js
terminusgps_install/templates/terminusgps_install/create_asset.html
terminusgps_install/templates/terminusgps_install/dashboard.html
terminusgps_install/templates/terminusgps_install/layout.html
terminusgps_install/templates/terminusgps_install/scan_vin.html
terminusgps_install/templates/terminusgps_install/scan_vin_success.html
terminusgps_install/templates/terminusgps_install/partials/_create_asset.html
terminusgps_install/templates/terminusgps_install/partials/_dashboard.html
terminusgps_install/templates/terminusgps_install/partials/_scan_vin.html
terminusgps_install/templates/terminusgps_install/partials/_scan_vin_success.html
terminusgps_install-1.0.0.dist-info/METADATA
terminusgps_install-1.0.0.dist-info/WHEEL
terminusgps_install-1.0.0.dist-info/licenses/COPYING
terminusgps_install-1.0.0.dist-info/RECORD
