Metadata-Version: 2.4
Name: terminusgps-install
Version: 1.0.0
Summary: Terminus GPS Install Django application
Project-URL: Documentation, https://docs.terminusgps.com/apps/install/
Project-URL: Repository, https://github.com/terminusgps/terminusgps-install
Author-email: Blake Nall <blake@terminusgps.com>
License-File: COPYING
Classifier: License :: OSI Approved :: GNU General Public License v3 or later (GPLv3+)
Classifier: Operating System :: OS Independent
Classifier: Programming Language :: Python :: 3
Classifier: Programming Language :: Python :: 3.12
Classifier: Programming Language :: Python :: 3.13
Requires-Python: >=3.12
Requires-Dist: django>=5.2.1
Requires-Dist: pillow>=11.2.1
Requires-Dist: python-terminusgps>=36.6.0
